timpypi/__init__.py
timpypi/tiktok.py
timpypi/utils.py
timpypi-3.6.0.dist-info/LICENSE
timpypi-3.6.0.dist-info/METADATA
timpypi-3.6.0.dist-info/WHEEL
timpypi-3.6.0.dist-info/top_level.txt
timpypi-3.6.0.dist-info/RECORD
