Metadata-Version: 2.1
Name: timpypi
Version: 3.6.0
Summary: Pakages for Odoo Developer
Author: Bùi Đức Tuấn (Tim)
Author-email: buiductuan12081995@gmail.com
License-File: LICENSE
Requires-Dist: tabulate
